protolog/__init__.py
protolog/tcp.py
protolog/test_tcp.py
protolog/test_udp.py
protolog/udp.py
protolog-24.1.0.dist-info/LICENSE
protolog-24.1.0.dist-info/METADATA
protolog-24.1.0.dist-info/WHEEL
protolog-24.1.0.dist-info/entry_points.txt
protolog-24.1.0.dist-info/top_level.txt
protolog-24.1.0.dist-info/RECORD
